mcp_server_my_mac/__init__.py
mcp_server_my_mac/__main__.py
mcp_server_my_mac/server.py
mcp_server_my_mac/readers/load_conda_info.py
mcp_server_my_mac/readers/load_system_profiler.py
mseep_mcp_my_mac-0.1.4.dist-info/METADATA
mseep_mcp_my_mac-0.1.4.dist-info/WHEEL
mseep_mcp_my_mac-0.1.4.dist-info/entry_points.txt
mseep_mcp_my_mac-0.1.4.dist-info/licenses/LICENSE
mseep_mcp_my_mac-0.1.4.dist-info/RECORD
